opening_hours/__init__.py
opening_hours/helpers.py
opening_hours/parse_opening_hours.py
opening_hours/patterns.py
opening_hours/models/__init__.py
opening_hours/models/day.py
opening_hours/models/days.py
opening_hours/models/time.py
opening_hours/models/times.py
parse_opening_hours-0.4.2.dist-info/LICENSE
parse_opening_hours-0.4.2.dist-info/METADATA
parse_opening_hours-0.4.2.dist-info/WHEEL
parse_opening_hours-0.4.2.dist-info/top_level.txt
parse_opening_hours-0.4.2.dist-info/RECORD
