Metadata-Version: 2.1
Name: parse-opening-hours
Version: 0.4.2
Summary: Parses opening hours from various human-readable strings into a standard JSON format
Home-page: https://github.com/MoralCode/parse-opening-hours
Author: Adrian Edwards
License: MIT
Platform: UNKNOWN
Classifier: License :: OSI Approved :: MIT License
Classifier: Programming Language :: Python :: 3
Classifier: Programming Language :: Python :: 3.8
Requires-Dist: pyparsing
